amcards/__helpers.py
amcards/__init__.py
amcards/amcards.py
amcards/exceptions.py
amcards/models.py
python_amcards-1.7.5.dist-info/licenses/LICENSE
python_amcards-1.7.5.dist-info/METADATA
python_amcards-1.7.5.dist-info/WHEEL
python_amcards-1.7.5.dist-info/top_level.txt
python_amcards-1.7.5.dist-info/RECORD
