Metadata-Version: 2.4
Name: python-amcards
Version: 1.7.5
Summary: A wrapper for the AMcards API.
Home-page: https://github.com/simonesestili/python-amcards
Author: Simone Sestili
Author-email: simone.sestili@amcards.com
Classifier: Development Status :: 5 - Production/Stable
Classifier: Intended Audience :: Developers
Classifier: License :: OSI Approved :: Apache Software License
Classifier: Natural Language :: English
Classifier: Programming Language :: Python :: 3
Classifier: Programming Language :: Python :: 3.10
License-File: LICENSE
Requires-Dist: requests>=2
Dynamic: author
Dynamic: author-email
Dynamic: classifier
Dynamic: description
Dynamic: description-content-type
Dynamic: home-page
Dynamic: license-file
Dynamic: requires-dist
Dynamic: summary
